{
  "nome": "Gold City",
  "imagem": "icon_cartas/speed/Gold_City_SSR.png", 
  "eventos": {
    "Eventos únicos": [
      {
        "nome": "(❯) Pride",
        "detalhes": [
          "Energy +20"
        ]
      },
      {
        "nome": "(❯❯) Struggle",
        "detalhes": [
          "Energy +10",
          "Stamina +10"
        ]
      },
      {
        "nome": "(❯❯❯) One Step",
        "detalhes": [
          "Stamina +10",
          "Keen Eye hint +1"
        ]
      }
    ],
    "Eventos aleatórios": [
      {
        "nome": "08:36 / Crap, I Overslept",
        "detalhes": [
          "\\033[1mOpção de cima\\033[0m",
          "Mood -1",
          "Skill points +45",
          "Gold City bond +5",
          "\\033[1mOpção de baixo\\033[0m",
          "Energy +10",
          "Wisdom +5",
          "Gold City bond +5"
        ]
      },
      {
        "nome": "13:12 / Lunch Break, Gotta Get Myself Together",
        "detalhes": [
          "\\033[1mOpção de cima\\033[0m",
          "Skill points +30",
          "Gold City bond +5",
          "\\033[1mOpção de baixo\\033[0m",
          "Skill 'A Small Breather' +1",
          "Gold City bond +5"
        ]
      }
    ]
  }
}
